karpyncho/__init__.py
karpyncho/stdout_context/__init__.py
tests/__init__.py
tests/test_init.py
karpyncho_stdout_context-0.1.3.dist-info/LICENSE.txt
karpyncho_stdout_context-0.1.3.dist-info/METADATA
karpyncho_stdout_context-0.1.3.dist-info/WHEEL
karpyncho_stdout_context-0.1.3.dist-info/top_level.txt
karpyncho_stdout_context-0.1.3.dist-info/RECORD
